{
    "root": {
        "data": {
            "storeName": "Area 420- Dundas St",
            "storeThemeOverrides": {
                "palette": {
                    "primary": {
                        "main": "#368118",
                        "contrastText": "#ffffff",
                        "light": "#368118",
                        "dark": "#368118"
                    },
                    "secondary": {
                        "main": "#ffffff",
                        "contrastText": "#000000",
                        "light": "#ffffff",
                        "dark": "#ffffff"
                    },
                    "background": {
                        "paper": "#F4F4F4",
                        "default": "#ffffff"
                    }
                },
                "typography": {
                    "fontFamily": "Roboto, sans-serif",
                    "fontWeightLight": 300,
                    "fontWeightRegular": 400,
                    "fontWeightMedium": 500,
                    "fontWeightBold": 700
                }
            },
            "locationDetails": {
                "Name": "",
                "Address": {
                    "AddressLine1": "226 Dundas St. ",
                    "AddressLine2": "08ef38c7-e2d2-45dc-9a07-974cfb76f7c1",
                    "City": "London",
                    "StateCode": "ON",
                    "StateName": "Ontario",
                    "CountryCode": "CA",
                    "CountryName": "Canada",
                    "Zip": "N6A1H3"
                },
                "StoreHours": {
                    "Monday": {
                        "Open": {
                            "Hour": 9,
                            "Minute": 0
                        },
                        "Close": {
                            "Hour": 23,
                            "Minute": 0
                        }
                    },
                    "Tuesday": {
                        "Open": {
                            "Hour": 9,
                            "Minute": 0
                        },
                        "Close": {
                            "Hour": 23,
                            "Minute": 0
                        }
                    },
                    "Wednesday": {
                        "Open": {
                            "Hour": 9,
                            "Minute": 0
                        },
                        "Close": {
                            "Hour": 23,
                            "Minute": 0
                        }
                    },
                    "Thursday": {
                        "Open": {
                            "Hour": 9,
                            "Minute": 0
                        },
                        "Close": {
                            "Hour": 23,
                            "Minute": 0
                        }
                    },
                    "Friday": {
                        "Open": {
                            "Hour": 9,
                            "Minute": 0
                        },
                        "Close": {
                            "Hour": 23,
                            "Minute": 0
                        }
                    },
                    "Saturday": {
                        "Open": {
                            "Hour": 9,
                            "Minute": 0
                        },
                        "Close": {
                            "Hour": 23,
                            "Minute": 0
                        }
                    },
                    "Sunday": {
                        "Open": {
                            "Hour": 9,
                            "Minute": 0
                        },
                        "Close": {
                            "Hour": 23,
                            "Minute": 0
                        }
                    }
                },
                "StorePhoneNumbers": [],
                "LicenseDetails": {
                    "Id": "075ea98c-b313-460d-8d67-af9f23a2a252",
                    "CompanyId": 318117,
                    "LocationId": 318120,
                    "LicenseNumber": "CRSA1266909"
                },
                "AgeLimit": 19,
                "TimeZone": {
                    "Standard": "IANA",
                    "Name": "America/New_York"
                },
                "Taxes": {
                    "PricingScheme": "Inclusive"
                }
            },
            "storeLogoURL": "https://cdn.covasoftware.com//logo/318117/de808f66-3030-40ef-8675-823c0fea5308.jpg",
            "ageVerified": true,
            "ageLimit": 19,
            "redirectTo": "/products?topCategory=Flower&categoryFilter=Flower",
            "ageGateEnabled": true,
            "metas": [],
            "customerId": "2023-04-12T16:56:39.349Z",
            "privacyPolicyUrl": "08ef38c7-e2d2-45dc-9a07-974cfb76f7c1",
            "termsOfServiceUrl": "08ef38c7-e2d2-45dc-9a07-974cfb76f7c1",
            "licenseHolderName": "08ef38c7-e2d2-45dc-9a07-974cfb76f7c1",
            "FaviconUrl": "08ef38c7-e2d2-45dc-9a07-974cfb76f7c1",
            "clarityTrackingCode": "qjpqb4wkrn",
            "clarityTrackingEnabled": true,
            "ENV": {
                "AGE_GATE_BYPASS_PASSWORD": "UGFzcw"
            }
        }
    },
    "products": {
        "data": {
            "ecommerceEnabled": true,
            "accountsEnabled": false,
            "ageGateEnabled": true,
            "itemCount": 0,
            "items": [],
            "categories": [
                {
                    "id": 1169,
                    "name": "Flower",
                    "img": "https://cdn.covasoftware.com/categories/Flower.png",
                    "classification_id": 58537,
                    "order": 0,
                    "children": [],
                    "parentId": "08ef38c7-e2d2-45dc-9a07-974cfb76f7c1"
                },
                {
                    "id": 1170,
                    "name": "Edibles",
                    "img": "https://cdn.covasoftware.com/categories/Edibles.png",
                    "classification_id": 58545,
                    "order": 1,
                    "children": [],
                    "parentId": "08ef38c7-e2d2-45dc-9a07-974cfb76f7c1"
                },
                {
                    "id": 1171,
                    "name": "Beverages",
                    "img": "https://cdn.covasoftware.com/categories/Beverages.png",
                    "classification_id": 58538,
                    "order": 2,
                    "children": [],
                    "parentId": "08ef38c7-e2d2-45dc-9a07-974cfb76f7c1"
                },
                {
                    "id": 1172,
                    "name": "Pre-Roll",
                    "img": "https://cdn.covasoftware.com/categories/InfusedPreRoll.png",
                    "classification_id": 58541,
                    "order": 3,
                    "children": [],
                    "parentId": "08ef38c7-e2d2-45dc-9a07-974cfb76f7c1"
                },
                {
                    "id": 1173,
                    "name": "Vapes",
                    "img": "https://cdn.covasoftware.com/categories/Vapes.png",
                    "classification_id": 58546,
                    "order": 4,
                    "children": [],
                    "parentId": "08ef38c7-e2d2-45dc-9a07-974cfb76f7c1"
                },
                {
                    "id": 1174,
                    "name": "Concentrates",
                    "img": "https://cdn.covasoftware.com/categories/Concentrates.png",
                    "classification_id": 58540,
                    "order": 5,
                    "children": [],
                    "parentId": "08ef38c7-e2d2-45dc-9a07-974cfb76f7c1"
                },
                {
                    "id": 1175,
                    "name": "Capsules",
                    "img": "https://cdn.covasoftware.com/categories/Capsule.png",
                    "classification_id": 58539,
                    "order": 6,
                    "children": [],
                    "parentId": "08ef38c7-e2d2-45dc-9a07-974cfb76f7c1"
                },
                {
                    "id": 1176,
                    "name": "Oil",
                    "img": "https://cdn.covasoftware.com/categories/Oil.png",
                    "classification_id": 58544,
                    "order": 7,
                    "children": [],
                    "parentId": "08ef38c7-e2d2-45dc-9a07-974cfb76f7c1"
                },
                {
                    "id": 1177,
                    "name": "Topicals",
                    "img": "https://cdn.covasoftware.com/categories/Topical.png",
                    "classification_id": 58543,
                    "order": 8,
                    "children": [],
                    "parentId": "08ef38c7-e2d2-45dc-9a07-974cfb76f7c1"
                },
                {
                    "id": 1178,
                    "name": "Seeds",
                    "img": "https://cdn.covasoftware.com/categories/Seeds.png",
                    "classification_id": 58542,
                    "order": 9,
                    "children": [],
                    "parentId": "08ef38c7-e2d2-45dc-9a07-974cfb76f7c1"
                },
                {
                    "id": 1179,
                    "name": "Accessories",
                    "img": "https://cdn.covasoftware.com/categories/Accessories.png",
                    "classification_id": 61020,
                    "order": 10,
                    "children": [],
                    "parentId": "08ef38c7-e2d2-45dc-9a07-974cfb76f7c1"
                }
            ],
            "user": "08ef38c7-e2d2-45dc-9a07-974cfb76f7c1",
            "isLoadingMedicalProducts": false,
            "stores": [],
            "store": {
                "id": 318120,
                "name": "Area 420- Dundas St",
                "logo": "https://cdn.covasoftware.com//logo/318117/de808f66-3030-40ef-8675-823c0fea5308.jpg",
                "host": "aca-ecom-web-prod.niceisland-d70b2c0f.westus.azurecontainerapps.io",
                "address": {
                    "AddressLine1": "226 Dundas St. ",
                    "AddressLine2": "08ef38c7-e2d2-45dc-9a07-974cfb76f7c1",
                    "City": "London",
                    "StateCode": "ON",
                    "StateName": "Ontario",
                    "CountryCode": "CA",
                    "CountryName": "Canada",
                    "Zip": "N6A1H3"
                },
                "primaryDomainUrl": "08ef38c7-e2d2-45dc-9a07-974cfb76f7c1"
            },
            "isDynamicDomain": false
        }
    },
    "routes/products/products/route": {
        "data": {
            "currentCategory": "Flower",
            "checkboxFilters": {
                "categoryFilter": [
                    {
                        "id": "category-Flower",
                        "name": "categoryFilter",
                        "value": "Flower",
                        "label": "Flower"
                    },
                    {
                        "id": "category-Edibles",
                        "name": "categoryFilter",
                        "value": "Edibles",
                        "label": "Edibles"
                    },
                    {
                        "id": "category-Beverages",
                        "name": "categoryFilter",
                        "value": "Beverages",
                        "label": "Beverages"
                    },
                    {
                        "id": "category-Pre-Roll",
                        "name": "categoryFilter",
                        "value": "Pre-Roll",
                        "label": "Pre-Roll"
                    },
                    {
                        "id": "category-Vapes",
                        "name": "categoryFilter",
                        "value": "Vapes",
                        "label": "Vapes"
                    },
                    {
                        "id": "category-Concentrates",
                        "name": "categoryFilter",
                        "value": "Concentrates",
                        "label": "Concentrates"
                    },
                    {
                        "id": "category-Capsules",
                        "name": "categoryFilter",
                        "value": "Capsules",
                        "label": "Capsules"
                    },
                    {
                        "id": "category-Oil",
                        "name": "categoryFilter",
                        "value": "Oil",
                        "label": "Oil"
                    },
                    {
                        "id": "category-Topicals",
                        "name": "categoryFilter",
                        "value": "Topicals",
                        "label": "Topicals"
                    },
                    {
                        "id": "category-Seeds",
                        "name": "categoryFilter",
                        "value": "Seeds",
                        "label": "Seeds"
                    },
                    {
                        "id": "category-Accessories",
                        "name": "categoryFilter",
                        "value": "Accessories",
                        "label": "Accessories"
                    }
                ],
                "priceFilter": [
                    {
                        "id": "price-25",
                        "name": "priceLessThanEq",
                        "value": "25",
                        "label": "Under $25",
                        "checked": false
                    },
                    {
                        "id": "price-50",
                        "name": "priceLessThanEq",
                        "value": "50",
                        "label": "Under $50",
                        "checked": false
                    },
                    {
                        "id": "price-100",
                        "name": "priceGreaterThanEq",
                        "value": "100",
                        "label": "Over $100",
                        "checked": false
                    }
                ],
                "netWeightFilter": [
                    {
                        "id": "netWeight-0.5",
                        "name": "netWeightFilter",
                        "value": "0.5",
                        "label": "0.5g",
                        "checked": false
                    },
                    {
                        "id": "netWeight-1",
                        "name": "netWeightFilter",
                        "value": "1",
                        "label": "1g",
                        "checked": false
                    },
                    {
                        "id": "netWeight-3.5",
                        "name": "netWeightFilter",
                        "value": "3.5",
                        "label": "3.5g",
                        "checked": false
                    },
                    {
                        "id": "netWeight-7",
                        "name": "netWeightFilter",
                        "value": "7",
                        "label": "7g",
                        "checked": false
                    },
                    {
                        "id": "netWeight-14",
                        "name": "netWeightFilter",
                        "value": "14",
                        "label": "14g",
                        "checked": false
                    },
                    {
                        "id": "netWeight-28",
                        "name": "netWeightFilter",
                        "value": "28",
                        "label": "28g",
                        "checked": false
                    }
                ],
                "subCategoryFilter": []
            },
            "dynamicFilters": {
                "strainFilter": [
                    {
                        "id": "Hybrid",
                        "name": "strainFilter",
                        "value": "Hybrid",
                        "label": "Hybrid"
                    },
                    {
                        "id": "Indica",
                        "name": "strainFilter",
                        "value": "Indica",
                        "label": "Indica"
                    },
                    {
                        "id": "Sativa",
                        "name": "strainFilter",
                        "value": "Sativa",
                        "label": "Sativa"
                    }
                ],
                "strainTypeFilter": [],
                "moodFilter": [],
                "brandFilter": [],
                "dominantTerpeneFilter": []
            },
            "products": [
                {
                    "ProductName": "EASTCANN - Permanent Marker - Hybrid - 3.5g",
                    "PrimaryAssetUrl": "/images/3d19d85d-ca03-4a68-a4a6-9932eea14660",
                    "DisplayPrice": 31.99,
                    "SalePrice": "08ef38c7-e2d2-45dc-9a07-974cfb76f7c1",
                    "QuantityInStock": 6,
                    "CategoryBreadCrumb": "Flower",
                    "ShortDescription": "",
                    "LongDescription": "EastCann Permanent Marker is a high THC hybrid strain crossed between Biscotti S1, Jealousy and Sherb BX. Delivering pungent flavours of soapy funk with hints of candy and floral gas tones, it's visually stunning in appearance. Highlighting bright emerald green buds contrasted by purple leaves and orange hairs that are dense with beautiful frosty trichomes.",
                    "NetWeight": 3.5,
                    "ThcMin": 30,
                    "ThcMax": 35,
                    "ThcUnit": "Percent",
                    "TotalThcMin": 30,
                    "TotalThcMax": 35,
                    "TotalThcUnit": "Percent",
                    "CbdMin": 0,
                    "CbdMax": 1,
                    "CbdUnit": "Percent",
                    "DateCreated": "2024-05-30T01:22:12.423Z",
                    "CatalogSku": "A1Q0XEMA",
                    "Strain": "Hybrid",
                    "CatalogProductID": "b63e1448-673b-4b91-bba9-c84acdef3d75",
                    "MeasurementType": "SingleUnit",
                    "SeoSlug": "eastcann-permanent-marker-hybrid-35g",
                    "HasTierPrices": false,
                    "TierPrices": "08ef38c7-e2d2-45dc-9a07-974cfb76f7c1",
                    "Brand": "",
                    "Moods": [],
                    "DominantTerpenes": [],
                    "ProductLicenseType": "",
                    "StrainType": ""
                },
                {
                    "ProductName": "Super Toast - Sgt. Pineapple - Hybrid - 7g",
                    "PrimaryAssetUrl": "/images/e1396fde-73ab-4689-9aad-660bd22b229e",
                    "DisplayPrice": 31.99,
                    "SalePrice": "08ef38c7-e2d2-45dc-9a07-974cfb76f7c1",
                    "QuantityInStock": 3,
                    "CategoryBreadCrumb": "Flower",
                    "ShortDescription": "",
                    "LongDescription": "-",
                    "NetWeight": 7,
                    "ThcMin": 28,
                    "ThcMax": 34,
                    "ThcUnit": "Percent",
                    "TotalThcMin": 28,
                    "TotalThcMax": 34,
                    "TotalThcUnit": "Percent",
                    "CbdMin": 0,
                    "CbdMax": 1,
                    "CbdUnit": "Percent",
                    "DateCreated": "2023-06-21T23:47:09.69Z",
                    "CatalogSku": "WD6MH7MV",
                    "Strain": "Hybrid",
                    "CatalogProductID": "0a81af8c-393e-4417-ad58-8f62f3326cdd",
                    "MeasurementType": "SingleUnit",
                    "SeoSlug": "super-toast-sgt-pineapple-hybrid-7g",
                    "HasTierPrices": false,
                    "TierPrices": "08ef38c7-e2d2-45dc-9a07-974cfb76f7c1",
                    "Brand": "Super Toast",
                    "Moods": [],
                    "DominantTerpenes": [],
                    "ProductLicenseType": "",
                    "StrainType": ""
                },
                {
                    "ProductName": "LowKey by MTL Cannabis - Cookie'z - Sativa - 7g",
                    "PrimaryAssetUrl": "/images/6e0f4c95-ceb5-4bfb-a0ea-c24b4e4d383d",
                    "DisplayPrice": 39.99,
                    "SalePrice": "08ef38c7-e2d2-45dc-9a07-974cfb76f7c1",
                    "QuantityInStock": 2,
                    "CategoryBreadCrumb": "Flower",
                    "ShortDescription": "",
                    "LongDescription": "LowKey’s Cookie’z (Platinum Cookies x Ice Cream) flower glitters under bright light, captivating the eye as its scent grabs the nose with a wave of cream and sweetness, as its name suggests, and the barest hint of spice, pine and citrus for depth. Its trichome layer is dense enough to obscure leaves that range from sea foam to emerald, interspersed with indigo. Our recipe is complete with the saffron orange threads this rare sativa phenotype exhibits throughout its robust and compact flowers.",
                    "NetWeight": 7,
                    "ThcMin": 29,
                    "ThcMax": 34,
                    "ThcUnit": "Percent",
                    "TotalThcMin": 29,
                    "TotalThcMax": 34,
                    "TotalThcUnit": "Percent",
                    "CbdMin": 0,
                    "CbdMax": 6,
                    "CbdUnit": "Percent",
                    "DateCreated": "2024-03-14T01:08:10.806Z",
                    "CatalogSku": "KKUYWUGM",
                    "Strain": "Sativa",
                    "CatalogProductID": "e59e201e-04d6-47ea-a3b2-8ca7618f356b",
                    "MeasurementType": "SingleUnit",
                    "SeoSlug": "lowkey-by-mtl-cannabis-cookiez-sativa-7g",
                    "HasTierPrices": false,
                    "TierPrices": "08ef38c7-e2d2-45dc-9a07-974cfb76f7c1",
                    "Brand": "",
                    "Moods": [],
                    "DominantTerpenes": [],
                    "ProductLicenseType": "",
                    "StrainType": ""
                },
                {
                    "ProductName": "Spinach - GMO Cookies - Indica - 14g",
                    "PrimaryAssetUrl": "/images/c32e1755-7ce3-4a66-93eb-fe8d5ba71ee0",
                    "DisplayPrice": 73.99,
                    "SalePrice": "08ef38c7-e2d2-45dc-9a07-974cfb76f7c1",
                    "QuantityInStock": 3,
                    "CategoryBreadCrumb": "Flower",
                    "ShortDescription": "",
                    "LongDescription": "Don't let the name deceive you. GMO (Garlic, Mushroom, Onion) Cookies has an unmistakably sweet and savoury taste and is one of the most popular indica strains out there. You can't make a soup out of it, but it sure goes nicely in a bowl.",
                    "NetWeight": 14,
                    "ThcMin": 27,
                    "ThcMax": 33,
                    "ThcUnit": "Percent",
                    "TotalThcMin": 27,
                    "TotalThcMax": 33,
                    "TotalThcUnit": "Percent",
                    "CbdMin": 0,
                    "CbdMax": 1,
                    "CbdUnit": "Percent",
                    "DateCreated": "2023-11-09T00:30:47.252Z",
                    "CatalogSku": "05UDRNAN",
                    "Strain": "Indica",
                    "CatalogProductID": "010b7780-0a64-4f27-98b8-39ee3bb60f3f",
                    "MeasurementType": "SingleUnit",
                    "SeoSlug": "spinach-gmo-cookies-indica-14g",
                    "HasTierPrices": false,
                    "TierPrices": "08ef38c7-e2d2-45dc-9a07-974cfb76f7c1",
                    "Brand": "Spinach",
                    "Moods": [],
                    "DominantTerpenes": [],
                    "ProductLicenseType": "",
                    "StrainType": ""
                },
                {
                    "ProductName": "Catch Me Outside - Rooster Call - Sativa - 3.5g",
                    "PrimaryAssetUrl": "/images/de7e58e1-4939-4b31-8059-86736346e451",
                    "DisplayPrice": 19.99,
                    "SalePrice": "08ef38c7-e2d2-45dc-9a07-974cfb76f7c1",
                    "QuantityInStock": 10,
                    "CategoryBreadCrumb": "Flower",
                    "ShortDescription": "",
                    "LongDescription": "Catch Me Outside is a 100% outdoor grown brand from Quebec offering quality products without taking themselves too seriously. Rooster Call offers strong THC sativa strains. The current strains and terpenes are indicated on the packaging. All Catch Me Outside flower are thoughtfully hand dried, hand trimmed and hand packaged. High-quality expectations but also affordable and sustainable. Out is the new in? Catch me outside!",
                    "NetWeight": 3.5,
                    "ThcMin": 28,
                    "ThcMax": 33,
                    "ThcUnit": "Percent",
                    "TotalThcMin": 28,
                    "TotalThcMax": 33,
                    "TotalThcUnit": "Percent",
                    "CbdMin": 0,
                    "CbdMax": 2,
                    "CbdUnit": "Percent",
                    "DateCreated": "2023-04-12T17:41:18.934Z",
                    "CatalogSku": "BMAA2KTF",
                    "Strain": "Sativa",
                    "CatalogProductID": "db6a467c-9f7e-4daa-b33a-726a9a5bc7ea",
                    "MeasurementType": "SingleUnit",
                    "SeoSlug": "catch-me-outside-rooster-call-sativa-35g",
                    "HasTierPrices": false,
                    "TierPrices": "08ef38c7-e2d2-45dc-9a07-974cfb76f7c1",
                    "Brand": "Catch Me Outside",
                    "Moods": [],
                    "DominantTerpenes": [],
                    "ProductLicenseType": "",
                    "StrainType": ""
                },
                {
                    "ProductName": "Spinach - Blue Thai - Sativa - 28g",
                    "PrimaryAssetUrl": "/images/1ef81dad-0aa7-4674-82a2-5b565a07ce54",
                    "DisplayPrice": 111.99,
                    "SalePrice": "08ef38c7-e2d2-45dc-9a07-974cfb76f7c1",
                    "QuantityInStock": 5,
                    "CategoryBreadCrumb": "Flower",
                    "ShortDescription": "",
                    "LongDescription": "All you need is blue skies and some Blue Thai. Spinach® Blue Thai is our ode to everything awesome about dried flower. Our take on this cultivar is a straight sativa strain with an undeniable, blast off level of potency from the first puff. We’re also highlighting the classic fruity, skunky, and citrusy flavours and aromas that come from a puckering lineage of Sour Blueberry and Lemon Thai through a trio of familiar yet harmonious terpenes — limonene, caryophyllene, and humulene. So, the next time you pop this in a bowl or a pre-roll, get ready to say, ‘My, oh my, that’s some good Blue Thai.",
                    "NetWeight": 28,
                    "ThcMin": 27,
                    "ThcMax": 33,
                    "ThcUnit": "Percent",
                    "TotalThcMin": 27,
                    "TotalThcMax": 33,
                    "TotalThcUnit": "Percent",
                    "CbdMin": 0,
                    "CbdMax": 6,
                    "CbdUnit": "Percent",
                    "DateCreated": "2025-07-10T01:47:18.232Z",
                    "CatalogSku": "X0D1QXTE",
                    "Strain": "Sativa",
                    "CatalogProductID": "d4ddc5e4-9816-407e-ab48-33c32893ed34",
                    "MeasurementType": "SingleUnit",
                    "SeoSlug": "spinach-blue-thai-sativa-28g",
                    "HasTierPrices": false,
                    "TierPrices": "08ef38c7-e2d2-45dc-9a07-974cfb76f7c1",
                    "Brand": "",
                    "Moods": [],
                    "DominantTerpenes": [],
                    "ProductLicenseType": "",
                    "StrainType": ""
                },
                {
                    "ProductName": "Bleuh - Original Sativa - 3.5g",
                    "PrimaryAssetUrl": "/images/bfbd2d2a-3949-4ac8-bb6a-2a339c5297b7",
                    "DisplayPrice": 28.99,
                    "SalePrice": "08ef38c7-e2d2-45dc-9a07-974cfb76f7c1",
                    "QuantityInStock": 10,
                    "CategoryBreadCrumb": "Flower",
                    "ShortDescription": "",
                    "LongDescription": "Bleuh Original Sativa is a recreational cannabis product intended for provincial retailers in the form of dried flowers. Our rotating limited edition strains are meticulously chosen by our sommeliers for outstanding quality and high THC levels. Original Sativa provides a continuously updated assortment of flowers. Cured for 14 days and grown in Quebec. Terpenes vary depending on the rotating strains. Batches are diligently selected for high quality.",
                    "NetWeight": 3.5,
                    "ThcMin": 27,
                    "ThcMax": 33,
                    "ThcUnit": "Percent",
                    "TotalThcMin": 27,
                    "TotalThcMax": 33,
                    "TotalThcUnit": "Percent",
                    "CbdMin": 0.1,
                    "CbdMax": 1,
                    "CbdUnit": "Percent",
                    "DateCreated": "2025-01-03T07:45:19.825Z",
                    "CatalogSku": "NC1N5TBA",
                    "Strain": "Sativa",
                    "CatalogProductID": "d28175ce-2f56-4abb-892c-3d1c197d8ce9",
                    "MeasurementType": "SingleUnit",
                    "SeoSlug": "bleuh-original-sativa-35g",
                    "HasTierPrices": false,
                    "TierPrices": "08ef38c7-e2d2-45dc-9a07-974cfb76f7c1",
                    "Brand": "",
                    "Moods": [],
                    "DominantTerpenes": [],
                    "ProductLicenseType": "",
                    "StrainType": ""
                },
                {
                    "ProductName": "Super Toast - Chill Mint - Hybrid - 7g",
                    "PrimaryAssetUrl": "/images/a47962f2-86b9-4250-b9ab-db70c8721f11",
                    "DisplayPrice": 26.99,
                    "SalePrice": "08ef38c7-e2d2-45dc-9a07-974cfb76f7c1",
                    "QuantityInStock": 5,
                    "CategoryBreadCrumb": "Flower",
                    "ShortDescription": "",
                    "LongDescription": "A herby hybrid with fresh minty aromas and a sniff of gas. Ground from whole buds, fluffy and fresh. No grinder needed. Super Toast. Always Ready.",
                    "NetWeight": 7,
                    "ThcMin": 27,
                    "ThcMax": 33,
                    "ThcUnit": "Percent",
                    "TotalThcMin": 27,
                    "TotalThcMax": 33,
                    "TotalThcUnit": "Percent",
                    "CbdMin": 0,
                    "CbdMax": 1,
                    "CbdUnit": "Percent",
                    "DateCreated": "2024-11-20T23:40:50.502Z",
                    "CatalogSku": "38C8MRZP",
                    "Strain": "Hybrid",
                    "CatalogProductID": "2f5b3834-43b3-47e3-aafa-fac1832c7c81",
                    "MeasurementType": "SingleUnit",
                    "SeoSlug": "super-toast-chill-mint-hybrid-7g",
                    "HasTierPrices": false,
                    "TierPrices": "08ef38c7-e2d2-45dc-9a07-974cfb76f7c1",
                    "Brand": "",
                    "Moods": [],
                    "DominantTerpenes": [],
                    "ProductLicenseType": "",
                    "StrainType": ""
                },
                {
                    "ProductName": "The Loud Plug - With Love from Scarborough - Craft Collective - Hybrid - 7g",
                    "PrimaryAssetUrl": "/images/dc9ee3b7-8c8a-447e-94f6-db3c76809941",
                    "DisplayPrice": 57.89,
                    "SalePrice": "08ef38c7-e2d2-45dc-9a07-974cfb76f7c1",
                    "QuantityInStock": 6,
                    "CategoryBreadCrumb": "Flower",
                    "ShortDescription": "",
                    "LongDescription": "With Love from Scarborough - Craft Collective is our homage to The Loud Plug's home town and the craft producers we are partnering with to bring this offer to life. The highest quality Ontario craft flower sourced form craft growers throughout the province. Our focus is on flavour, aroma, high THC and terpenes.",
                    "NetWeight": 7,
                    "ThcMin": 27,
                    "ThcMax": 33,
                    "ThcUnit": "Percent",
                    "TotalThcMin": 27,
                    "TotalThcMax": 33,
                    "TotalThcUnit": "Percent",
                    "CbdMin": 0,
                    "CbdMax": 6,
                    "CbdUnit": "Percent",
                    "DateCreated": "2023-09-21T01:29:17.403Z",
                    "CatalogSku": "FT32FCD8",
                    "Strain": "Indica",
                    "CatalogProductID": "a1c56057-d493-47c6-b214-1cf871426c71",
                    "MeasurementType": "SingleUnit",
                    "SeoSlug": "the-loud-plug-with-love-from-scarborough-craft-collective-hybrid-7g",
                    "HasTierPrices": false,
                    "TierPrices": "08ef38c7-e2d2-45dc-9a07-974cfb76f7c1",
                    "Brand": "The Loud Plug",
                    "Moods": [],
                    "DominantTerpenes": [],
                    "ProductLicenseType": "",
                    "StrainType": ""
                },
                {
                    "ProductName": "Catch Me Outside - Couch Potato - Indica - 3.5g",
                    "PrimaryAssetUrl": "/images/dc95adf1-9f48-4b8f-8208-30ce7168130c",
                    "DisplayPrice": 19.99,
                    "SalePrice": "08ef38c7-e2d2-45dc-9a07-974cfb76f7c1",
                    "QuantityInStock": 13,
                    "CategoryBreadCrumb": "Flower",
                    "ShortDescription": "",
                    "LongDescription": "Catch Me Outside is an outdoor growth brand, from Quebec, offering first quality of products without taking themselves too seriously. Couch Potato offers a rotation of strong THC indica strains with the current strain and terpenes written on the packaging. All Catch Me Outside flower is thoughtfully hang dried, hand trimmed and hand packaged. High-quality expectations but through a more affordable positioning. Out is the new in? Catch Me Outside!",
                    "NetWeight": 3.5,
                    "ThcMin": 28,
                    "ThcMax": 33,
                    "ThcUnit": "Percent",
                    "TotalThcMin": 28,
                    "TotalThcMax": 33,
                    "TotalThcUnit": "Percent",
                    "CbdMin": 0,
                    "CbdMax": 2,
                    "CbdUnit": "Percent",
                    "DateCreated": "2023-04-12T17:41:18.947Z",
                    "CatalogSku": "840Z0241",
                    "Strain": "Indica",
                    "CatalogProductID": "b38afd8e-1119-4fed-a214-af09eadffff7",
                    "MeasurementType": "SingleUnit",
                    "SeoSlug": "catch-me-outside-couch-potato-indica-35g",
                    "HasTierPrices": false,
                    "TierPrices": "08ef38c7-e2d2-45dc-9a07-974cfb76f7c1",
                    "Brand": "Catch Me Outside",
                    "Moods": [],
                    "DominantTerpenes": [],
                    "ProductLicenseType": "",
                    "StrainType": ""
                },
                {
                    "ProductName": "Pepe - 11 Week Pink - Indica - 28g",
                    "PrimaryAssetUrl": "/images/f0264f50-d60d-4604-9c90-28a4a4c45a9e",
                    "DisplayPrice": 104.99,
                    "SalePrice": "08ef38c7-e2d2-45dc-9a07-974cfb76f7c1",
                    "QuantityInStock": 3,
                    "CategoryBreadCrumb": "Flower",
                    "ShortDescription": "",
                    "LongDescription": "A familiar favourite amongst legacy consumers, 11 week pink is a indica-leaning hybrid that has long been beloved across Canada for its strong aromas, colourful flowers and high THC potential. 11 Week Pink delivers aromas of butterscotch and coffee with sourdough undertones. Flashy pink hairs permeate this dense and flavourful bud for a full sensory experience guaranteed to delight. Packaged in resealable pouch with a humidity pack to preserve freshness.",
                    "NetWeight": 28,
                    "ThcMin": 25,
                    "ThcMax": 32,
                    "ThcUnit": "Percent",
                    "TotalThcMin": 25,
                    "TotalThcMax": 32,
                    "TotalThcUnit": "Percent",
                    "CbdMin": 0,
                    "CbdMax": 2,
                    "CbdUnit": "Percent",
                    "DateCreated": "2023-11-09T00:33:24.649Z",
                    "CatalogSku": "6QG0N7CU",
                    "Strain": "Indica",
                    "CatalogProductID": "cf1a45fa-c393-43dd-b046-f0d3084474ea",
                    "MeasurementType": "SingleUnit",
                    "SeoSlug": "pepe-11-week-pink-indica-28g",
                    "HasTierPrices": false,
                    "TierPrices": "08ef38c7-e2d2-45dc-9a07-974cfb76f7c1",
                    "Brand": "Pepe",
                    "Moods": [],
                    "DominantTerpenes": [],
                    "ProductLicenseType": "",
                    "StrainType": ""
                },
                {
                    "ProductName": "Coterie - Lemon Cherry Gelato - Hybrid - 7g",
                    "PrimaryAssetUrl": "/images/670ed50b-772d-4904-ab22-90f5db32cae5",
                    "DisplayPrice": 49.99,
                    "SalePrice": "08ef38c7-e2d2-45dc-9a07-974cfb76f7c1",
                    "QuantityInStock": 2,
                    "CategoryBreadCrumb": "Flower",
                    "ShortDescription": "",
                    "LongDescription": "As the name suggests, expect sweet, sherbet-like flavours of lemon, blueberries, and cherries with great bag appeal. Lemon Cherry Gelato is an exotic cross of legendary strains; Sunset Sherbet x Thin Mint GSC x Lemon Haze, originally bred by BackPack Boyz. The densely frosted flowers show tones of light and dark green, accented by bright orange hairs. Craft designated and hand-packed in home compostable jars.",
                    "NetWeight": 7,
                    "ThcMin": 26,
                    "ThcMax": 32,
                    "ThcUnit": "Percent",
                    "TotalThcMin": 26,
                    "TotalThcMax": 32,
                    "TotalThcUnit": "Percent",
                    "CbdMin": 0,
                    "CbdMax": 1,
                    "CbdUnit": "Percent",
                    "DateCreated": "2024-03-14T01:04:28.287Z",
                    "CatalogSku": "DNU80GXX",
                    "Strain": "Hybrid",
                    "CatalogProductID": "fed2a850-7872-4d87-aede-48be7c2fa8ea",
                    "MeasurementType": "SingleUnit",
                    "SeoSlug": "coterie-lemon-cherry-gelato-hybrid-7g",
                    "HasTierPrices": false,
                    "TierPrices": "08ef38c7-e2d2-45dc-9a07-974cfb76f7c1",
                    "Brand": "",
                    "Moods": [],
                    "DominantTerpenes": [],
                    "ProductLicenseType": "",
                    "StrainType": ""
                },
                {
                    "ProductName": "Simply Bare - BC Organic Black Zoap - Indica - 3.5g",
                    "PrimaryAssetUrl": "/images/cbe042eb-3d85-48a4-9eef-a13789d76ad0",
                    "DisplayPrice": 41.99,
                    "SalePrice": "08ef38c7-e2d2-45dc-9a07-974cfb76f7c1",
                    "QuantityInStock": 7,
                    "CategoryBreadCrumb": "Flower",
                    "ShortDescription": "",
                    "LongDescription": "Bred by Odessey Genetics, our BC Organic Black Zoap offers complex aromas and flavours that blend sweet notes with a soapy and gassy profile. Expect excellent flavour translation, as you envelop your senses with this robust indica hybrid. Grown in our organic living soil and hand tended, expect nothing but pristine buds packed safely in our premium glass jars.",
                    "NetWeight": 3.5,
                    "ThcMin": 26,
                    "ThcMax": 32,
                    "ThcUnit": "Percent",
                    "TotalThcMin": 26,
                    "TotalThcMax": 32,
                    "TotalThcUnit": "Percent",
                    "CbdMin": 0,
                    "CbdMax": 1,
                    "CbdUnit": "Percent",
                    "DateCreated": "2025-08-14T18:15:56.051Z",
                    "CatalogSku": "2RXK5B62",
                    "Strain": "Indica",
                    "CatalogProductID": "89b71657-0b1e-4e2b-b93e-ec3dbb36b2ba",
                    "MeasurementType": "SingleUnit",
                    "SeoSlug": "simply-bare-bc-organic-black-zoap-indica-35g",
                    "HasTierPrices": false,
                    "TierPrices": "08ef38c7-e2d2-45dc-9a07-974cfb76f7c1",
                    "Brand": "",
                    "Moods": [],
                    "DominantTerpenes": [],
                    "ProductLicenseType": "",
                    "StrainType": ""
                },
                {
                    "ProductName": "Simply Bare - BC Organic Luv Affair - Indica - 3.5g",
                    "PrimaryAssetUrl": "/images/c1375274-f5aa-4d75-a9ee-969a2f223b8a",
                    "DisplayPrice": 41.99,
                    "SalePrice": "08ef38c7-e2d2-45dc-9a07-974cfb76f7c1",
                    "QuantityInStock": 6,
                    "CategoryBreadCrumb": "Flower",
                    "ShortDescription": "",
                    "LongDescription": "An exclusive offering from Odessey Genetics, our BC Organic Luv Affair brings an irresistible blend of fruity, skunky and gassy notes. Her dense and frosty buds will fill the room with bold aromas, that translate perfectly to the flavours. Grown in our organic living soil, hand tended, and never irradiated, we hand pack each jar ensuring only the best buds make the cut.",
                    "NetWeight": 3.5,
                    "ThcMin": 26,
                    "ThcMax": 32,
                    "ThcUnit": "Percent",
                    "TotalThcMin": 26,
                    "TotalThcMax": 32,
                    "TotalThcUnit": "Percent",
                    "CbdMin": 0,
                    "CbdMax": 1,
                    "CbdUnit": "Percent",
                    "DateCreated": "2025-07-10T01:47:52.9Z",
                    "CatalogSku": "TPHY4AW8",
                    "Strain": "Indica",
                    "CatalogProductID": "1902c334-7600-4402-ab3e-8b8578948ec8",
                    "MeasurementType": "SingleUnit",
                    "SeoSlug": "simply-bare-bc-organic-luv-affair-indica-35g",
                    "HasTierPrices": false,
                    "TierPrices": "08ef38c7-e2d2-45dc-9a07-974cfb76f7c1",
                    "Brand": "",
                    "Moods": [],
                    "DominantTerpenes": [],
                    "ProductLicenseType": "",
                    "StrainType": ""
                },
                {
                    "ProductName": "Nugz - Sativa - 14g",
                    "PrimaryAssetUrl": "/images/b52fa1b9-f813-440f-8539-171e56fbb283",
                    "DisplayPrice": 61.99,
                    "SalePrice": "08ef38c7-e2d2-45dc-9a07-974cfb76f7c1",
                    "QuantityInStock": 2,
                    "CategoryBreadCrumb": "Flower",
                    "ShortDescription": "",
                    "LongDescription": "What's better than tearing into a fresh sack of beautiful big buds? This is a sack packed with only the best buds we can offer. Nugz Sativa, a rotating offering of sativa strains from Cannara's genetic library. You can expect strains like Cuban Linx, Early Lemon Berry, Jigglers, and new drops! Get in, get out, get Nugz!",
                    "NetWeight": 14,
                    "ThcMin": 26,
                    "ThcMax": 32,
                    "ThcUnit": "Percent",
                    "TotalThcMin": 26,
                    "TotalThcMax": 32,
                    "TotalThcUnit": "Percent",
                    "CbdMin": 0,
                    "CbdMax": 2,
                    "CbdUnit": "Percent",
                    "DateCreated": "2024-03-14T01:05:57.085Z",
                    "CatalogSku": "NN0UJWU3",
                    "Strain": "Sativa",
                    "CatalogProductID": "85e0cc07-93f8-43f4-9c2c-b4ab915de50a",
                    "MeasurementType": "SingleUnit",
                    "SeoSlug": "nugz-sativa-14g",
                    "HasTierPrices": false,
                    "TierPrices": "08ef38c7-e2d2-45dc-9a07-974cfb76f7c1",
                    "Brand": "",
                    "Moods": [],
                    "DominantTerpenes": [],
                    "ProductLicenseType": "",
                    "StrainType": ""
                },
                {
                    "ProductName": "Bud Lafleur - Ak-47 - Sativa - 3.5g",
                    "PrimaryAssetUrl": "/images/0993114c-5c4e-4fe2-b156-83f4f294728c",
                    "DisplayPrice": 28.99,
                    "SalePrice": "08ef38c7-e2d2-45dc-9a07-974cfb76f7c1",
                    "QuantityInStock": 9,
                    "CategoryBreadCrumb": "Flower",
                    "ShortDescription": "",
                    "LongDescription": "Discover All Kush 47, a sativa dominant strain with high THC potency created by crossing the legendary All Kush 47 with Thai. This strain features deep green buds adorned with bright orange pistils and coated in sugary trichomes. All Kush 47 has sweet and spicy aromas and earthy undertones. The dominant terpenes are beta-myrcene, ocimene and caryophyllene, which contribute to its unique and rich profile. Grown indoors in Pointe-Claire, Quebec, our meticulous cultivation process ensures high quality. Each plant is hand harvested, whole plant hang dried, hand trimmed and cured cold and slow for a minimum of 14 days. Finally, each package is carefully hand packaged to maintain its quality. Elevate your cannabis experience with All Kush 47, where potency meets craftsmanship.",
                    "NetWeight": 3.5,
                    "ThcMin": 26,
                    "ThcMax": 31,
                    "ThcUnit": "Percent",
                    "TotalThcMin": 26,
                    "TotalThcMax": 31,
                    "TotalThcUnit": "Percent",
                    "CbdMin": 0,
                    "CbdMax": 2,
                    "CbdUnit": "Percent",
                    "DateCreated": "2024-11-20T23:40:48.181Z",
                    "CatalogSku": "UE5AKWGT",
                    "Strain": "Sativa",
                    "CatalogProductID": "e4a3c221-5591-457b-90a2-aa97eeb493e3",
                    "MeasurementType": "SingleUnit",
                    "SeoSlug": "bud-lafleur-ak-47-sativa-35g",
                    "HasTierPrices": false,
                    "TierPrices": "08ef38c7-e2d2-45dc-9a07-974cfb76f7c1",
                    "Brand": "",
                    "Moods": [],
                    "DominantTerpenes": [],
                    "ProductLicenseType": "",
                    "StrainType": ""
                },
                {
                    "ProductName": "Bud Lafleur - Banana Daddy - Indica - 3.5g",
                    "PrimaryAssetUrl": "/images/c1a49323-8248-4b1a-995b-2627f2be14c8",
                    "DisplayPrice": 28.99,
                    "SalePrice": "08ef38c7-e2d2-45dc-9a07-974cfb76f7c1",
                    "QuantityInStock": 4,
                    "CategoryBreadCrumb": "Flower",
                    "ShortDescription": "",
                    "LongDescription": "Banana Daddy is an indica strain with a high THC potency potential made by crossing Granddaddy Purp x Banana Hammock R1. Dense, chunky bud structure, deep green buds coated with frost-like trichomes, Banana Daddy delivers fruity aromas with a light diesel finish. The dominant terpenes are myrcene, ocimene and alpha-pinene. Grown indoors in Pointe-Claire, Quebec, we hand harvest, whole plant hang dry, hand trim, and slow cure.",
                    "NetWeight": 3.5,
                    "ThcMin": 25,
                    "ThcMax": 31,
                    "ThcUnit": "Percent",
                    "TotalThcMin": 25,
                    "TotalThcMax": 31,
                    "TotalThcUnit": "Percent",
                    "CbdMin": 0,
                    "CbdMax": 2,
                    "CbdUnit": "Percent",
                    "DateCreated": "2023-11-09T00:29:34.147Z",
                    "CatalogSku": "0W4HPKTD",
                    "Strain": "Indica",
                    "CatalogProductID": "5cee4baa-d9b3-42bb-bf71-c1b4055b37f7",
                    "MeasurementType": "SingleUnit",
                    "SeoSlug": "bud-lafleur-banana-daddy-indica-35g",
                    "HasTierPrices": false,
                    "TierPrices": "08ef38c7-e2d2-45dc-9a07-974cfb76f7c1",
                    "Brand": "",
                    "Moods": [],
                    "DominantTerpenes": [],
                    "ProductLicenseType": "",
                    "StrainType": ""
                },
                {
                    "ProductName": "Spinach - Blue Dream - Sativa - 3.5g",
                    "PrimaryAssetUrl": "/images/273ea376-ede2-46c2-b9cb-72c53af6a787",
                    "DisplayPrice": 23.99,
                    "SalePrice": "08ef38c7-e2d2-45dc-9a07-974cfb76f7c1",
                    "QuantityInStock": 10,
                    "CategoryBreadCrumb": "Flower",
                    "ShortDescription": "",
                    "LongDescription": "Originally from Cali, this sunny sativa strain is a legend in its own time. Once you taste the berry, citrus, sweetness of this strain, you might have to pinch yourself.",
                    "NetWeight": 3.5,
                    "ThcMin": 25,
                    "ThcMax": 31,
                    "ThcUnit": "Percent",
                    "TotalThcMin": 25,
                    "TotalThcMax": 31,
                    "TotalThcUnit": "Percent",
                    "CbdMin": 0,
                    "CbdMax": 2,
                    "CbdUnit": "Percent",
                    "DateCreated": "2023-04-12T16:59:54.375Z",
                    "CatalogSku": "QKLDYLND",
                    "Strain": "Sativa",
                    "CatalogProductID": "9e6b4d63-73ac-426d-950d-3bb3e5d909ad",
                    "MeasurementType": "SingleUnit",
                    "SeoSlug": "spinach-blue-dream-sativa-35g",
                    "HasTierPrices": false,
                    "TierPrices": "08ef38c7-e2d2-45dc-9a07-974cfb76f7c1",
                    "Brand": "Spinach",
                    "Moods": [],
                    "DominantTerpenes": [],
                    "ProductLicenseType": "",
                    "StrainType": ""
                },
                {
                    "ProductName": "SHRED - Funk Master - Hybrid - 7g",
                    "PrimaryAssetUrl": "/images/657299a5-b75d-486f-90ee-a2efcde2e60c",
                    "DisplayPrice": 32.99,
                    "SalePrice": "08ef38c7-e2d2-45dc-9a07-974cfb76f7c1",
                    "QuantityInStock": 3,
                    "CategoryBreadCrumb": "Flower",
                    "ShortDescription": "",
                    "LongDescription": "We've captured the essence of real dank nugs with skunky, gas and earthy aromas that bring the funk. A combination of sweet skunk, funky cheese and pungent diesel notes. Get down and get dank with Funk Master.",
                    "NetWeight": 7,
                    "ThcMin": 25,
                    "ThcMax": 31,
                    "ThcUnit": "Percent",
                    "TotalThcMin": 25,
                    "TotalThcMax": 31,
                    "TotalThcUnit": "Percent",
                    "CbdMin": 0,
                    "CbdMax": 1,
                    "CbdUnit": "Percent",
                    "DateCreated": "2023-04-12T17:10:40.488Z",
                    "CatalogSku": "QC6GH6HM",
                    "Strain": "Indica",
                    "CatalogProductID": "b445d3b5-0d94-4c8b-9e60-759ee6e7ed97",
                    "MeasurementType": "SingleUnit",
                    "SeoSlug": "shred-funk-master-hybrid-7g",
                    "HasTierPrices": false,
                    "TierPrices": "08ef38c7-e2d2-45dc-9a07-974cfb76f7c1",
                    "Brand": "SHRED",
                    "Moods": [],
                    "DominantTerpenes": [],
                    "ProductLicenseType": "",
                    "StrainType": ""
                },
                {
                    "ProductName": "Redecan - Cold Creek Kush - Sativa - 1g",
                    "PrimaryAssetUrl": "/images/16a1da23-9431-4f9d-b5eb-5d3d66271c7e",
                    "DisplayPrice": 8.99,
                    "SalePrice": "08ef38c7-e2d2-45dc-9a07-974cfb76f7c1",
                    "QuantityInStock": 11,
                    "CategoryBreadCrumb": "Flower",
                    "ShortDescription": "",
                    "LongDescription": "Cold Creek Kush from Redecan is a cross between MK Ultra and fellow Colorado native Chemdawg 91, with dense, heart-shaped, light green buds full of trichomes and amber hairs. Grown in the Niagara region of Ontario, the strain has very strong THC potency and a recognizable dank smell, much like a forest after a rainfall. Its taste profile, informed by its beta-pinene, nerolidol, trans-caryophyllene, linalool and limonene terpene mix, is strongly herbal, earthy and woody, with fresh sour pine.",
                    "NetWeight": 1,
                    "ThcMin": 25,
                    "ThcMax": 31,
                    "ThcUnit": "Percent",
                    "TotalThcMin": 25,
                    "TotalThcMax": 31,
                    "TotalThcUnit": "Percent",
                    "CbdMin": 0,
                    "CbdMax": 1.5,
                    "CbdUnit": "Percent",
                    "DateCreated": "2023-04-12T16:56:39.349Z",
                    "CatalogSku": "V0EAUQNV",
                    "Strain": "Sativa",
                    "CatalogProductID": "08ef38c7-e2d2-45dc-9a07-974cfb76f7c1",
                    "MeasurementType": "SingleUnit",
                    "SeoSlug": "redecan-cold-creek-kush-sativa-1g",
                    "HasTierPrices": false,
                    "TierPrices": "08ef38c7-e2d2-45dc-9a07-974cfb76f7c1",
                    "Brand": "Redecan",
                    "Moods": [],
                    "DominantTerpenes": [],
                    "ProductLicenseType": "",
                    "StrainType": ""
                }
            ],
            "sortOrder": "BestMatch",
            "searchFilter": "08ef38c7-e2d2-45dc-9a07-974cfb76f7c1",
            "baseCDNHostName": "https://cdn.covasoftware.com",
            "ecommerceEnabled": true,
            "storeName": "Area 420- Dundas St",
            "cannabinoidsConfig": {
                "thcSource": "08ef38c7-e2d2-45dc-9a07-974cfb76f7c1"
            },
            "isStoreInCanada": true
        }
    }
}